CHANGELOG.txt
LICENCE.txt
MANIFEST.in
README.txt
setup.py
RelayMe/__init__.py
RelayMe.egg-info/PKG-INFO
RelayMe.egg-info/SOURCES.txt
RelayMe.egg-info/dependency_links.txt
RelayMe.egg-info/top_level.txt