Metadata-Version: 2.1
Name: RelayMe
Version: 0.0.1
Summary: Sends emails with chosen email relay service
Home-page: 
Author: Elijah Phifer
Author-email: elijahphifer9@gmail.com
License: MIT
Keywords: mail
Classifier: Development Status :: 5 - Production/Stable
Classifier: Intended Audience :: Education
Classifier: Operating System :: Microsoft :: Windows :: Windows 10
Classifier: License :: OSI Approved :: MIT License
Classifier: Programming Language :: Python :: 3
License-File: LICENCE.txt
